{
  "entries": {
    "tap": {
      "argoproj/tap": {
        "revision": "d61cc39825ace4e53a3d5bf2bd07519a535d0aa5"
      },
      "derailed/k9s": {
        "revision": "b3ae3684454053ffbf9c7ab4a57a0723bf7a9052"
      },
      "getantibody/tap": {
        "revision": "1808a80e113fa05188f028d57afcea26b964067f"
      },
      "homebrew/bundle": {
        "revision": "4b9a95355a4784a6839821ec58467f8e1ed96ad7"
      },
      "homebrew/cask": {
        "revision": "489c4688c4ce603d351dbc3a969e90db039b046d"
      },
      "homebrew/cask-fonts": {
        "revision": "4002bfa454011d0bb83f8897637055bbe5f9550a"
      },
      "homebrew/cask-versions": {
        "revision": "e883610196d9b72a0f3bc506d737dec3c8c46b83"
      },
      "homebrew/core": {
        "revision": "14beeb3b2ed43a753be9ab97c45a4c1d4669c449"
      },
      "d12frosted/emacs-plus": {
        "revision": "51ddb7f9eeefcce8836a08f23483085372a1b805"
      }
    },
    "brew": {
      "antibody": {
        "version": "6.0.1",
        "bottle": {
          "cellar": ":any_skip_relocation",
          "prefix": "/usr/local",
          "files": {
            "catalina": {
              "url": "https://homebrew.bintray.com/bottles/antibody-6.0.1.catalina.bottle.tar.gz",
              "sha256": "5c3ec35f32bb0ba5a254c7ea09675251dfa73ec5c0066a3a28a7fd637065e026"
            },
            "mojave": {
              "url": "https://homebrew.bintray.com/bottles/antibody-6.0.1.mojave.bottle.tar.gz",
              "sha256": "44120733359210252f9b57d7d4d96ab46acb13828a3b65fdb001e639cc46a31a"
            },
            "high_sierra": {
              "url": "https://homebrew.bintray.com/bottles/antibody-6.0.1.high_sierra.bottle.tar.gz",
              "sha256": "ccea6fb02d1df23fc2438993b2434a8826904d3be4779d5efc5310ae2fbddfb2"
            }
          }
        }
      },
      "awscli": {
        "version": "2.0.23",
        "bottle": {
          "cellar": "/usr/local/Cellar",
          "prefix": "/usr/local",
          "files": {
            "catalina": {
              "url": "https://homebrew.bintray.com/bottles/awscli-2.0.23.catalina.bottle.tar.gz",
              "sha256": "4ccd883386ceed5eab14ab86f5bba121a24ee346b381b9471d63b35ebe89f70a"
            },
            "mojave": {
              "url": "https://homebrew.bintray.com/bottles/awscli-2.0.23.mojave.bottle.tar.gz",
              "sha256": "562514476c72adc0c8136f74ec0ffdca5792a586689de15b40bf199d2b6195fe"
            },
            "high_sierra": {
              "url": "https://homebrew.bintray.com/bottles/awscli-2.0.23.high_sierra.bottle.tar.gz",
              "sha256": "a8982eb143136312e447741298be726c02b2eaa576322e0c683dca6e4bcfa0bb"
            }
          }
        }
      },
      "httpie": {
        "version": "2.1.0",
        "bottle": {
          "cellar": ":any_skip_relocation",
          "prefix": "/usr/local",
          "files": {
            "catalina": {
              "url": "https://homebrew.bintray.com/bottles/httpie-2.1.0.catalina.bottle.tar.gz",
              "sha256": "25f0e58f81a2cdd9cba772f07d67591533b4b31a2b970a356701aa046d4d9638"
            },
            "mojave": {
              "url": "https://homebrew.bintray.com/bottles/httpie-2.1.0.mojave.bottle.tar.gz",
              "sha256": "be158ebb4cfd327ebea02f7b8b8d63d093e474cd303eafff4a2b56b0611983a2"
            },
            "high_sierra": {
              "url": "https://homebrew.bintray.com/bottles/httpie-2.1.0.high_sierra.bottle.tar.gz",
              "sha256": "f331edb94183bfc5fa9de4b4abf148cc91a3a8b3c0e24cc1f5e6b0a4172dd34d"
            }
          }
        }
      },
      "erlang": {
        "version": "23.0.2",
        "bottle": {
          "cellar": ":any",
          "prefix": "/usr/local",
          "files": {
            "catalina": {
              "url": "https://homebrew.bintray.com/bottles/erlang-23.0.2.catalina.bottle.tar.gz",
              "sha256": "26f1fc19d139fe6d54e748abea071c2283b6262bb3583a0855d225bdfdb9f74b"
            },
            "mojave": {
              "url": "https://homebrew.bintray.com/bottles/erlang-23.0.2.mojave.bottle.tar.gz",
              "sha256": "64da31473e7668d3742cdbcf4ef815955665708a74d27e7b64f697a3f0f5f62b"
            },
            "high_sierra": {
              "url": "https://homebrew.bintray.com/bottles/erlang-23.0.2.high_sierra.bottle.tar.gz",
              "sha256": "644de29d8c3b4739a2bf1cf01b3c3042cbc3b8434fcaab869ecfdf9cdef1dc59"
            }
          }
        }
      },
      "emacs-plus": {
        "version": "HEAD-398afba",
        "bottle": null,
        "options": {
          "args": [
            "--head"
          ]
        }
      },
      "git": {
        "version": "2.27.0",
        "bottle": {
          "cellar": "/usr/local/Cellar",
          "prefix": "/usr/local",
          "files": {
            "catalina": {
              "url": "https://homebrew.bintray.com/bottles/git-2.27.0.catalina.bottle.tar.gz",
              "sha256": "5bfe46796926e48d2d78ee87e93195c0a36f7c70d9aa4ff8ab77277a6582441a"
            },
            "mojave": {
              "url": "https://homebrew.bintray.com/bottles/git-2.27.0.mojave.bottle.tar.gz",
              "sha256": "dffad4b938672dda3aef783f88cf38d67923f8f8e68df77b198476816fd37d4f"
            },
            "high_sierra": {
              "url": "https://homebrew.bintray.com/bottles/git-2.27.0.high_sierra.bottle.tar.gz",
              "sha256": "c9f1d9ac100e43a2e6f1df9785d98119d08bf144d862fb541c1212ccfb700041"
            }
          }
        }
      },
      "helm": {
        "version": "3.2.4",
        "bottle": {
          "cellar": ":any_skip_relocation",
          "prefix": "/usr/local",
          "files": {
            "catalina": {
              "url": "https://homebrew.bintray.com/bottles/helm-3.2.4.catalina.bottle.tar.gz",
              "sha256": "e78753400abf0cb0cb71af8b1e16217d26c703e020e075d4a95b563dd7cb4a4e"
            },
            "mojave": {
              "url": "https://homebrew.bintray.com/bottles/helm-3.2.4.mojave.bottle.tar.gz",
              "sha256": "a3c27f74fa2422412c276c98a6dc62b6e746e0c569bfceed74cd0b7c75939c5d"
            },
            "high_sierra": {
              "url": "https://homebrew.bintray.com/bottles/helm-3.2.4.high_sierra.bottle.tar.gz",
              "sha256": "a390ab2d2b29e7cb7a214ea7983f8c37b659a9c90b71988f6c7754455b49a65f"
            }
          }
        }
      },
      "fnm": {
        "version": "1.21.0",
        "bottle": false
      },
      "jq": {
        "version": "1.6",
        "bottle": {
          "cellar": ":any",
          "prefix": "/usr/local",
          "files": {
            "catalina": {
              "url": "https://homebrew.bintray.com/bottles/jq-1.6.catalina.bottle.1.tar.gz",
              "sha256": "820a3c85fcbb63088b160c7edf125d7e55fc2c5c1d51569304499c9cc4b89ce8"
            },
            "mojave": {
              "url": "https://homebrew.bintray.com/bottles/jq-1.6.mojave.bottle.1.tar.gz",
              "sha256": "71f0e76c5b22e5088426c971d5e795fe67abee7af6c2c4ae0cf4c0eb98ed21ff"
            },
            "high_sierra": {
              "url": "https://homebrew.bintray.com/bottles/jq-1.6.high_sierra.bottle.1.tar.gz",
              "sha256": "dffcffa4ea13e8f0f2b45c5121e529077e135ae9a47254c32182231662ee9b72"
            },
            "sierra": {
              "url": "https://homebrew.bintray.com/bottles/jq-1.6.sierra.bottle.1.tar.gz",
              "sha256": "bb4d19dc026c2d72c53eed78eaa0ab982e9fcad2cd2acc6d13e7a12ff658e877"
            }
          }
        }
      },
      "neovim": {
        "version": "0.4.3",
        "bottle": {
          "cellar": "/usr/local/Cellar",
          "prefix": "/usr/local",
          "files": {
            "catalina": {
              "url": "https://homebrew.bintray.com/bottles/neovim-0.4.3.catalina.bottle.tar.gz",
              "sha256": "389ab254794ea04df8a106bf281c227c4fdee27c609d52951f32b9a0239031d6"
            },
            "mojave": {
              "url": "https://homebrew.bintray.com/bottles/neovim-0.4.3.mojave.bottle.tar.gz",
              "sha256": "fb6cc38c45be4650a4a750a314cec27f6f7643dc7c22a1f5abae347e1b39b388"
            },
            "high_sierra": {
              "url": "https://homebrew.bintray.com/bottles/neovim-0.4.3.high_sierra.bottle.tar.gz",
              "sha256": "b2f7450e005f4eb22bfaf650fe7741fa8629393a947b4dd48c9f91e7fc258113"
            }
          }
        }
      },
      "markdown": {
        "version": "1.0.1",
        "bottle": {
          "cellar": ":any_skip_relocation",
          "prefix": "/usr/local",
          "files": {
            "catalina": {
              "url": "https://homebrew.bintray.com/bottles/markdown-1.0.1.catalina.bottle.tar.gz",
              "sha256": "35864422386d1390de813462b697b604813bc3a7caac7bf3fd172335e25b2a55"
            },
            "mojave": {
              "url": "https://homebrew.bintray.com/bottles/markdown-1.0.1.mojave.bottle.tar.gz",
              "sha256": "343d406a2a4838499afa96395733e0d61f91c725a4693e6c5b3c49293e5297e8"
            },
            "high_sierra": {
              "url": "https://homebrew.bintray.com/bottles/markdown-1.0.1.high_sierra.bottle.tar.gz",
              "sha256": "c7b43e96e9967731f9f9395152dca0d1535eb270a953aeccfe24dc99d3941f97"
            },
            "sierra": {
              "url": "https://homebrew.bintray.com/bottles/markdown-1.0.1.sierra.bottle.tar.gz",
              "sha256": "47715f7beb1f434a5d52e6977c7f6ad584be7b0d970dacb00ef5965bd162858d"
            },
            "el_capitan": {
              "url": "https://homebrew.bintray.com/bottles/markdown-1.0.1.el_capitan.bottle.tar.gz",
              "sha256": "a5b025bc09c8b274507cfc5c86da6350560477f24ce109dd5a79f2dafa97d805"
            },
            "yosemite": {
              "url": "https://homebrew.bintray.com/bottles/markdown-1.0.1.yosemite.bottle.tar.gz",
              "sha256": "5e1b8b5388f1b4ceefe3fae528ae83e2fa3f9ed9f27668e8faded36b9ec3274e"
            },
            "mavericks": {
              "url": "https://homebrew.bintray.com/bottles/markdown-1.0.1.mavericks.bottle.tar.gz",
              "sha256": "66fffda1a29fd9e2dcddcb52fb9606f21d897bf4680583626b612a95d27b1e04"
            }
          }
        }
      },
      "macvim": {
        "version": "8.2-163_2",
        "bottle": {
          "cellar": ":any",
          "prefix": "/usr/local",
          "files": {
            "catalina": {
              "url": "https://homebrew.bintray.com/bottles/macvim-8.2-163_2.catalina.bottle.tar.gz",
              "sha256": "316de5c66d247961309a072307784c1073f650b5fac87af32c67ca80bf62b0c1"
            },
            "mojave": {
              "url": "https://homebrew.bintray.com/bottles/macvim-8.2-163_2.mojave.bottle.tar.gz",
              "sha256": "56c860f1dd98ebe374cf0721bac29e830dfc9665a5fe4f2dd26697d58713f9e1"
            },
            "high_sierra": {
              "url": "https://homebrew.bintray.com/bottles/macvim-8.2-163_2.high_sierra.bottle.tar.gz",
              "sha256": "4b67795ddfcf1018ac1f260231f8a534072edbcb7b4ff060296667fd965a0abb"
            }
          }
        }
      },
      "mas": {
        "version": "1.7.0",
        "bottle": {
          "cellar": ":any",
          "prefix": "/usr/local",
          "files": {
            "catalina": {
              "url": "https://homebrew.bintray.com/bottles/mas-1.7.0.catalina.bottle.tar.gz",
              "sha256": "b985d100947063ee94961f7f1290f232786634b869d20d56bd553197cf91188b"
            },
            "mojave": {
              "url": "https://homebrew.bintray.com/bottles/mas-1.7.0.mojave.bottle.tar.gz",
              "sha256": "c7005c34a3cf38d23f98e9cc238a0deae61f50ea5dfbcf51a34cc689a9db315e"
            }
          }
        }
      },
      "nmap": {
        "version": "7.80_1",
        "bottle": {
          "cellar": "/usr/local/Cellar",
          "prefix": "/usr/local",
          "files": {
            "catalina": {
              "url": "https://homebrew.bintray.com/bottles/nmap-7.80_1.catalina.bottle.tar.gz",
              "sha256": "ada1fae22e64234618a2df68d1ef43f4f0a186b80fb80ccce927c1679df9d66f"
            },
            "mojave": {
              "url": "https://homebrew.bintray.com/bottles/nmap-7.80_1.mojave.bottle.tar.gz",
              "sha256": "bc12b9340cf3c23ac9f5a4eb6102884baf556b2347f46c3971600b91fb081125"
            },
            "high_sierra": {
              "url": "https://homebrew.bintray.com/bottles/nmap-7.80_1.high_sierra.bottle.tar.gz",
              "sha256": "3cbc937428a7db08be8fa106b3a70ffad16f4a4d80808d2113490dd9ab60786c"
            },
            "sierra": {
              "url": "https://homebrew.bintray.com/bottles/nmap-7.80_1.sierra.bottle.tar.gz",
              "sha256": "afa1fde2e44927ccb36447a0ce1dde08927ae67fd789afeb3883a95bd61edbc4"
            }
          }
        }
      },
      "node": {
        "version": "14.4.0",
        "bottle": {
          "cellar": ":any",
          "prefix": "/usr/local",
          "files": {
            "catalina": {
              "url": "https://homebrew.bintray.com/bottles/node-14.4.0.catalina.bottle.tar.gz",
              "sha256": "7fbf484b2c921451809192dba684a838ba387a4affc1d4380ebb607f95ccf0ec"
            },
            "mojave": {
              "url": "https://homebrew.bintray.com/bottles/node-14.4.0.mojave.bottle.tar.gz",
              "sha256": "06ef204701e93bbcf3909dba4ac9d3ca1d4df00a980f03cbeab390be1c562d34"
            },
            "high_sierra": {
              "url": "https://homebrew.bintray.com/bottles/node-14.4.0.high_sierra.bottle.tar.gz",
              "sha256": "68c7e5ff3e93bda3795d954b83609282f9ccf3cbe8096affeb28179d1fc1bd1d"
            }
          }
        }
      },
      "pipenv": {
        "version": "2020.6.2",
        "bottle": {
          "cellar": ":any_skip_relocation",
          "prefix": "/usr/local",
          "files": {
            "catalina": {
              "url": "https://homebrew.bintray.com/bottles/pipenv-2020.6.2.catalina.bottle.tar.gz",
              "sha256": "12257ab59085420c2ad08dbe12236d9393d814ed387e8ab8f6e7acb730635321"
            },
            "mojave": {
              "url": "https://homebrew.bintray.com/bottles/pipenv-2020.6.2.mojave.bottle.tar.gz",
              "sha256": "82bd72857a8cebceca3f6ea44140d7391ac1d94c84406c6a5ea51e5e87b88a66"
            },
            "high_sierra": {
              "url": "https://homebrew.bintray.com/bottles/pipenv-2020.6.2.high_sierra.bottle.tar.gz",
              "sha256": "792be77485b744b5891613c4bf02b6d5544ff1da65b6a02b7c3c59c540e007b5"
            }
          }
        }
      },
      "swi-prolog": {
        "version": "8.2.0",
        "bottle": {
          "cellar": "/usr/local/Cellar",
          "prefix": "/usr/local",
          "files": {
            "catalina": {
              "url": "https://homebrew.bintray.com/bottles/swi-prolog-8.2.0.catalina.bottle.tar.gz",
              "sha256": "1353754ee8858e0929e958524adbba7301066c06e15da07ab62efbee0d8e7add"
            },
            "mojave": {
              "url": "https://homebrew.bintray.com/bottles/swi-prolog-8.2.0.mojave.bottle.tar.gz",
              "sha256": "d8ddd94fe8e3631cc32ce38a3a7c81a32c3a3798ada1d99779a82ea51c2305bb"
            },
            "high_sierra": {
              "url": "https://homebrew.bintray.com/bottles/swi-prolog-8.2.0.high_sierra.bottle.tar.gz",
              "sha256": "26e7b1f2bed68d5b79cfaeb59f1185f8f215bedda355876e08386b3b88bbebe5"
            }
          }
        }
      },
      "wget": {
        "version": "1.20.3_2",
        "bottle": {
          "cellar": "/usr/local/Cellar",
          "prefix": "/usr/local",
          "files": {
            "catalina": {
              "url": "https://homebrew.bintray.com/bottles/wget-1.20.3_2.catalina.bottle.tar.gz",
              "sha256": "ef65c759c5097a36323fa9c77756468649e8d1980a3a4e05695c05e39568967c"
            },
            "mojave": {
              "url": "https://homebrew.bintray.com/bottles/wget-1.20.3_2.mojave.bottle.tar.gz",
              "sha256": "28f4090610946a4eb207df102d841de23ced0d06ba31cb79e040d883906dcd4f"
            },
            "high_sierra": {
              "url": "https://homebrew.bintray.com/bottles/wget-1.20.3_2.high_sierra.bottle.tar.gz",
              "sha256": "91dd0caca9bd3f38c439d5a7b6f68440c4274945615fae035ff0a369264b8a2f"
            }
          }
        }
      },
      "yarn": {
        "version": "1.22.4",
        "bottle": false
      },
      "tmux": {
        "version": "3.1b",
        "bottle": {
          "cellar": ":any",
          "prefix": "/usr/local",
          "files": {
            "catalina": {
              "url": "https://homebrew.bintray.com/bottles/tmux-3.1b.catalina.bottle.tar.gz",
              "sha256": "f26bd0c3f5696350dcaf229d0fadaf6ab677c0ebbb550fc499ca0a37da59ab55"
            },
            "mojave": {
              "url": "https://homebrew.bintray.com/bottles/tmux-3.1b.mojave.bottle.tar.gz",
              "sha256": "e9995ca765078be9cfdef4f1b6a628bcded0e96e36649e084a7f5480d165547a"
            },
            "high_sierra": {
              "url": "https://homebrew.bintray.com/bottles/tmux-3.1b.high_sierra.bottle.tar.gz",
              "sha256": "7a04ece8143c0647be18bb14c160a984a5a9f855fa2ee888d21fc19374790ee5"
            }
          }
        }
      },
      "terminal-notifier": {
        "version": "2.0.0",
        "bottle": {
          "cellar": ":any_skip_relocation",
          "prefix": "/usr/local",
          "files": {
            "catalina": {
              "url": "https://homebrew.bintray.com/bottles/terminal-notifier-2.0.0.catalina.bottle.tar.gz",
              "sha256": "78eff95b7436480521ee68a8581ff2df0c615adefccd279486f2491f1b1c0a4b"
            },
            "mojave": {
              "url": "https://homebrew.bintray.com/bottles/terminal-notifier-2.0.0.mojave.bottle.tar.gz",
              "sha256": "9671c602326357b7397248bfb0cf062bc47f19add15b615e512f58545c387c31"
            },
            "high_sierra": {
              "url": "https://homebrew.bintray.com/bottles/terminal-notifier-2.0.0.high_sierra.bottle.tar.gz",
              "sha256": "f112656234f4100d23cc1a41b96f92a09974360a822c2ec0fb6f9970862c1a22"
            },
            "sierra": {
              "url": "https://homebrew.bintray.com/bottles/terminal-notifier-2.0.0.sierra.bottle.tar.gz",
              "sha256": "210cd525fad70bbaef40f092bc3478b1519f68f73c034990230d8b1cc61a8a7c"
            },
            "el_capitan": {
              "url": "https://homebrew.bintray.com/bottles/terminal-notifier-2.0.0.el_capitan.bottle.tar.gz",
              "sha256": "75ce68fd95fb502e20ccb25be72f7db12112ac1a4bdf5a70c140cd174ecbacf5"
            }
          }
        }
      },
      "starship": {
        "version": "0.42.0",
        "bottle": {
          "cellar": ":any_skip_relocation",
          "prefix": "/usr/local",
          "files": {
            "catalina": {
              "url": "https://homebrew.bintray.com/bottles/starship-0.42.0.catalina.bottle.tar.gz",
              "sha256": "b20531ed2fde6ddcad26f24f1e3ce63582633a0da0cbfb296df04b9325080d26"
            },
            "mojave": {
              "url": "https://homebrew.bintray.com/bottles/starship-0.42.0.mojave.bottle.tar.gz",
              "sha256": "ef100b0cba6d10b4506861d588ecd239aff541e838536ec1e63763c168049a4f"
            },
            "high_sierra": {
              "url": "https://homebrew.bintray.com/bottles/starship-0.42.0.high_sierra.bottle.tar.gz",
              "sha256": "e0ac6fdea4f4b79ad65ab6d54ab22204e6a4dbe37077825b308f763759abd225"
            }
          }
        }
      },
      "michaeldfallen/formula/git-radar": null,
      "zsh-history-substring-search": {
        "version": "1.0.2",
        "bottle": false
      },
      "tldr": {
        "version": "1.3.0_2",
        "bottle": {
          "cellar": ":any",
          "prefix": "/usr/local",
          "files": {
            "catalina": {
              "url": "https://homebrew.bintray.com/bottles/tldr-1.3.0_2.catalina.bottle.1.tar.gz",
              "sha256": "41a6db2e28eeae00ff6d1888948d8b7d0f01cd67b3f271341b856cded07ba6ca"
            },
            "mojave": {
              "url": "https://homebrew.bintray.com/bottles/tldr-1.3.0_2.mojave.bottle.1.tar.gz",
              "sha256": "7f10022d0c6648741457c2562bc5e521d8dd88dfc4c4d68d1c886739ffd7eb45"
            },
            "high_sierra": {
              "url": "https://homebrew.bintray.com/bottles/tldr-1.3.0_2.high_sierra.bottle.1.tar.gz",
              "sha256": "c932bd8516b6690c45dcbf90ced6ad94d4a0aa5a366de532fe90c4ab82b9a2ad"
            }
          }
        }
      },
      "htop": {
        "version": "2.2.0_1",
        "bottle": {
          "cellar": ":any",
          "prefix": "/usr/local",
          "files": {
            "catalina": {
              "url": "https://homebrew.bintray.com/bottles/htop-2.2.0_1.catalina.bottle.tar.gz",
              "sha256": "c06ff60960f64f5c8395f53d7419cbcce2a22ee87f0cb0138352c8a88111d21c"
            },
            "mojave": {
              "url": "https://homebrew.bintray.com/bottles/htop-2.2.0_1.mojave.bottle.tar.gz",
              "sha256": "77aa302765353b4085dcad52356d3264183e06310dda8d5bac64642299ea2902"
            },
            "high_sierra": {
              "url": "https://homebrew.bintray.com/bottles/htop-2.2.0_1.high_sierra.bottle.tar.gz",
              "sha256": "0ebfb655b91566ba31f8effc94d642a43305ff95bdc9b30b46fadc132e2ced0c"
            },
            "sierra": {
              "url": "https://homebrew.bintray.com/bottles/htop-2.2.0_1.sierra.bottle.tar.gz",
              "sha256": "ed93b86f011de155c5d261b8c9cc9cb81fd0017667bf3ebe26ee090716bcd650"
            }
          }
        }
      },
      "tree": {
        "version": "1.8.0",
        "bottle": {
          "cellar": ":any_skip_relocation",
          "prefix": "/usr/local",
          "files": {
            "catalina": {
              "url": "https://homebrew.bintray.com/bottles/tree-1.8.0.catalina.bottle.tar.gz",
              "sha256": "18f7984bdbab22251e9fc3c7832dbace5c7f7a77e8d63717bb0078385e2bf255"
            },
            "mojave": {
              "url": "https://homebrew.bintray.com/bottles/tree-1.8.0.mojave.bottle.tar.gz",
              "sha256": "7152288c457dd893de50fa9d6ac9a8599748564e1b3586eec8eff7057089051a"
            },
            "high_sierra": {
              "url": "https://homebrew.bintray.com/bottles/tree-1.8.0.high_sierra.bottle.tar.gz",
              "sha256": "107d965994381d34e90b58a62f1c306c1b8a698db2696cdd905ba65c801ecc3b"
            },
            "sierra": {
              "url": "https://homebrew.bintray.com/bottles/tree-1.8.0.sierra.bottle.tar.gz",
              "sha256": "07d980571469a0cc699c69a8726eee338f782ba61c041e58f01ddb2924d08aeb"
            }
          }
        }
      },
      "fzf": {
        "version": "0.21.1",
        "bottle": {
          "cellar": ":any_skip_relocation",
          "prefix": "/usr/local",
          "files": {
            "catalina": {
              "url": "https://homebrew.bintray.com/bottles/fzf-0.21.1.catalina.bottle.tar.gz",
              "sha256": "733f79496c3246979ca05eeb5677a5fd9e8ec532e69e8b2012102cacddba8ae6"
            },
            "mojave": {
              "url": "https://homebrew.bintray.com/bottles/fzf-0.21.1.mojave.bottle.tar.gz",
              "sha256": "3c03bb9715be153a0f776d06cf4acd436ad4faa4266f7bd875a0d37594291516"
            },
            "high_sierra": {
              "url": "https://homebrew.bintray.com/bottles/fzf-0.21.1.high_sierra.bottle.tar.gz",
              "sha256": "d15a616156eb92071f1cfc50f10366532af92ca1635d309162141ad67f785865"
            }
          }
        }
      },
      "fd": {
        "version": "8.1.1",
        "bottle": {
          "cellar": ":any_skip_relocation",
          "prefix": "/usr/local",
          "files": {
            "catalina": {
              "url": "https://homebrew.bintray.com/bottles/fd-8.1.1.catalina.bottle.tar.gz",
              "sha256": "4625e56da438b94dfe331a2fe1df759b140931241af097df91f29d8ac314f2d3"
            },
            "mojave": {
              "url": "https://homebrew.bintray.com/bottles/fd-8.1.1.mojave.bottle.tar.gz",
              "sha256": "d002e8d8de192b6fad189ff7830d4fe9fc7d4ca9e81aa5ac66bb5200c590703a"
            },
            "high_sierra": {
              "url": "https://homebrew.bintray.com/bottles/fd-8.1.1.high_sierra.bottle.tar.gz",
              "sha256": "c269bbc76090614e7262c81e1b21d784050a71a51a5921686845f0d3c0855400"
            }
          }
        }
      },
      "bat": {
        "version": "0.15.4",
        "bottle": {
          "cellar": ":any_skip_relocation",
          "prefix": "/usr/local",
          "files": {
            "catalina": {
              "url": "https://homebrew.bintray.com/bottles/bat-0.15.4.catalina.bottle.tar.gz",
              "sha256": "ae2c26d25a0dac35bd839a091f89201b5d9eee32ef613325426c7e8b8812d1a9"
            },
            "mojave": {
              "url": "https://homebrew.bintray.com/bottles/bat-0.15.4.mojave.bottle.tar.gz",
              "sha256": "40dea8577c06a08d3e3bd20a949245ff02ea85153d25f72a65cee03c1b1e1cf9"
            },
            "high_sierra": {
              "url": "https://homebrew.bintray.com/bottles/bat-0.15.4.high_sierra.bottle.tar.gz",
              "sha256": "59bed16f8a4741a9d92f62cb7c9965d1abe40dc5dd2323bc4f37e71330b1abf2"
            }
          }
        }
      },
      "direnv": {
        "version": "2.21.3",
        "bottle": {
          "cellar": ":any_skip_relocation",
          "prefix": "/usr/local",
          "files": {
            "catalina": {
              "url": "https://homebrew.bintray.com/bottles/direnv-2.21.3.catalina.bottle.tar.gz",
              "sha256": "3d27ce73fbfdf133817b8e25f217d935be47a2467aa2f008d8ae2ef0ffaeccf4"
            },
            "mojave": {
              "url": "https://homebrew.bintray.com/bottles/direnv-2.21.3.mojave.bottle.tar.gz",
              "sha256": "1b16dd8e83fd2463744faad358496812599d8844eb773c62947652958d20662d"
            },
            "high_sierra": {
              "url": "https://homebrew.bintray.com/bottles/direnv-2.21.3.high_sierra.bottle.tar.gz",
              "sha256": "4b5a41fc1184ff2362f9558b9e822821b350aae36a98ec81bb2c70c9f1bc9bed"
            }
          }
        }
      },
      "ripgrep": {
        "version": "12.1.1",
        "bottle": {
          "cellar": ":any",
          "prefix": "/usr/local",
          "files": {
            "catalina": {
              "url": "https://homebrew.bintray.com/bottles/ripgrep-12.1.1.catalina.bottle.tar.gz",
              "sha256": "60460d422253113af3ed60332104f309638942821c655332211a6bc2213c472c"
            },
            "mojave": {
              "url": "https://homebrew.bintray.com/bottles/ripgrep-12.1.1.mojave.bottle.tar.gz",
              "sha256": "de4b18789f5d9bc4aaa4d906501200ae4ece7a1971dd1b86e2b2d0a2c8e0d764"
            },
            "high_sierra": {
              "url": "https://homebrew.bintray.com/bottles/ripgrep-12.1.1.high_sierra.bottle.tar.gz",
              "sha256": "cfea5335bf4eccfb7cd1d93bec234d96bd49dce8d593ea966687f777909ba291"
            }
          }
        }
      },
      "path-extractor": {
        "version": "0.2.0",
        "bottle": {
          "cellar": ":any_skip_relocation",
          "prefix": "/usr/local",
          "files": {
            "catalina": {
              "url": "https://homebrew.bintray.com/bottles/path-extractor-0.2.0.catalina.bottle.tar.gz",
              "sha256": "f882b9d1c9ba8fdc8ba16d6bbad852034182636d9c968cfbacf8cc1e08009a7d"
            },
            "mojave": {
              "url": "https://homebrew.bintray.com/bottles/path-extractor-0.2.0.mojave.bottle.tar.gz",
              "sha256": "8feb5be3e88fa0370593d8d349a90b54ac953a504439ec61722cff7e843153cc"
            },
            "high_sierra": {
              "url": "https://homebrew.bintray.com/bottles/path-extractor-0.2.0.high_sierra.bottle.tar.gz",
              "sha256": "38faa134c10a82b9ac28077d6df73da8b1ce2fed2fb8fe4f24ddebb08c18b623"
            },
            "sierra": {
              "url": "https://homebrew.bintray.com/bottles/path-extractor-0.2.0.sierra.bottle.tar.gz",
              "sha256": "bf30c2d715d52035b57b640d849c21e1508fb189259b5e02343f8104f50d6624"
            },
            "el_capitan": {
              "url": "https://homebrew.bintray.com/bottles/path-extractor-0.2.0.el_capitan.bottle.tar.gz",
              "sha256": "90521da4fd1834db41fbf19b7b6ce9f82a943ab2412acd41b6c5d749146770e7"
            },
            "yosemite": {
              "url": "https://homebrew.bintray.com/bottles/path-extractor-0.2.0.yosemite.bottle.tar.gz",
              "sha256": "718512fe3585d82dee8d655c2ab534dac70d0b24a8164bcc012f0f2a65a55e5b"
            },
            "mavericks": {
              "url": "https://homebrew.bintray.com/bottles/path-extractor-0.2.0.mavericks.bottle.tar.gz",
              "sha256": "f883b0656efe0d31b35b98ab0c82d82f1fa827b39d3712136c49bae2363f539d"
            }
          }
        }
      },
      "go": {
        "version": "1.14.3",
        "bottle": {
          "cellar": "/usr/local/Cellar",
          "prefix": "/usr/local",
          "files": {
            "catalina": {
              "url": "https://homebrew.bintray.com/bottles/go-1.14.3.catalina.bottle.tar.gz",
              "sha256": "e3c4f834acba4e4db3f2b848860a040de1d8dec158545e8aaa3dd2f380c9c950"
            },
            "mojave": {
              "url": "https://homebrew.bintray.com/bottles/go-1.14.3.mojave.bottle.tar.gz",
              "sha256": "70ae2f7f10ccd4926be3f5f7482afe8f0d0fe78f0e4fa2eea05c20a80ffa9c6e"
            },
            "high_sierra": {
              "url": "https://homebrew.bintray.com/bottles/go-1.14.3.high_sierra.bottle.tar.gz",
              "sha256": "9b334b2eff3b1d40c74d89daeec0b08d4a0e331103c6c10c08d060e86605f61b"
            }
          }
        }
      },
      "ant": {
        "version": "1.10.8_1",
        "bottle": false
      },
      "maven": {
        "version": "3.6.3_1",
        "bottle": false
      },
      "gradle": {
        "version": "6.5",
        "bottle": false
      }
    },
    "cask": {
      "arq": {
        "version": "5.17.2",
        "options": {
          "full_name": "arq",
          "args": {
            "appdir": "/Applications"
          }
        }
      },
      "dash": {
        "version": "5.1.2",
        "options": {
          "full_name": "dash",
          "args": {
            "appdir": "/Applications"
          }
        }
      },
      "gpg-suite": {
        "version": "2019.2",
        "options": {
          "full_name": "gpg-suite",
          "args": {
            "appdir": "/Applications"
          }
        }
      },
      "hammerspoon": {
        "version": "0.9.77",
        "options": {
          "full_name": "hammerspoon",
          "args": {
            "appdir": "/Applications"
          }
        }
      },
      "imageoptim": {
        "version": "1.8.8",
        "options": {
          "full_name": "imageoptim",
          "args": {
            "appdir": "/Applications"
          }
        }
      },
      "iterm2": {
        "version": "3.3.8",
        "options": {
          "full_name": "iterm2",
          "args": {
            "appdir": "/Applications"
          }
        }
      },
      "kaleidoscope": {
        "version": "2.2.2-1376",
        "options": {
          "full_name": "kaleidoscope",
          "args": {
            "appdir": "/Applications"
          }
        }
      },
      "visual-studio-code": {
        "version": "1.32.3,a3db5be9b5c6ba46bb7555ec5d60178ecc2eaae4",
        "options": {
          "full_name": "visual-studio-code",
          "args": {
            "appdir": "/Applications"
          }
        }
      },
      "rectangle": {
        "version": "0.14",
        "options": {
          "full_name": "rectangle",
          "args": {
            "appdir": "/Applications"
          }
        }
      },
      "licecap": {
        "version": "1.30",
        "options": {
          "full_name": "licecap",
          "args": {
            "appdir": "/Applications"
          }
        }
      },
      "numi": {
        "version": "3.24.654",
        "options": {
          "full_name": "numi",
          "args": {
            "appdir": "/Applications"
          }
        }
      },
      "android-studio": {
        "version": "3.6.2.0,192.6308749",
        "options": {
          "full_name": "android-studio",
          "args": {
            "appdir": "/Applications"
          }
        }
      }
    }
  },
  "system": {
    "macos": {
      "catalina": {
        "HOMEBREW_VERSION": "2.4.0-69-g67c843b",
        "HOMEBREW_PREFIX": "/usr/local",
        "Homebrew/homebrew-core": "14beeb3b2ed43a753be9ab97c45a4c1d4669c449",
        "CLT": "11.0.33.17",
        "Xcode": "11.5",
        "macOS": "10.15.5"
      }
    }
  }
}
